ob_dj_survey/apis/__init__.py
ob_dj_survey/apis/survey/__init__.py
ob_dj_survey/apis/survey/permissions.py
ob_dj_survey/apis/survey/serializers.py
ob_dj_survey/apis/survey/urls.py
ob_dj_survey/apis/survey/views.py
ob_dj_survey/apis/user/__init__.py
ob_dj_survey/apis/user/serializers.py
ob_dj_survey/core/__init__.py
ob_dj_survey/core/survey/__init__.py
ob_dj_survey/core/survey/apps.py
ob_dj_survey/core/survey/managers.py
ob_dj_survey/core/survey/models.py
ob_dj_survey/core/survey/settings_validation.py
ob_dj_survey/core/survey/admin/__init__.py
ob_dj_survey/core/survey/migrations/0001_initial.py
ob_dj_survey/core/survey/migrations/0002_auto_20210921_2054.py
ob_dj_survey/core/survey/migrations/0003_auto_20211206_0600.py
ob_dj_survey/core/survey/migrations/0004_survey_name.py
ob_dj_survey/core/survey/migrations/0005_auto_20211210_1332.py
ob_dj_survey/core/survey/migrations/0006_auto_20211214_2201.py
ob_dj_survey/core/survey/migrations/0007_surveychoice_description.py
ob_dj_survey/core/survey/migrations/0008_auto_20211221_1901.py
ob_dj_survey/core/survey/migrations/0009_auto_20211221_1930.py
ob_dj_survey/core/survey/migrations/0010_remove_survey_section.py
ob_dj_survey/core/survey/migrations/0011_auto_20211222_1418.py
ob_dj_survey/core/survey/migrations/0012_auto_20211223_1935.py
ob_dj_survey/core/survey/migrations/0013_survey_is_active.py
ob_dj_survey/core/survey/migrations/0014_auto_20220315_1650_squashed_0017_auto_20220412_0417.py
ob_dj_survey/core/survey/migrations/0015_auto_20220412_2350.py
ob_dj_survey/core/survey/migrations/0016_auto_20220413_0549.py
ob_dj_survey/core/survey/migrations/__init__.py
ob_dj_survey/utils/__init__.py
ob_dj_survey/utils/factories.py
ob_dj_survey/utils/helpers.py
ob_dj_survey/utils/models.py
ob_dj_survey/utils/serializers.py
ob_dj_survey/utils/validations.py
ob_dj_survey-0.1.3.dist-info/METADATA
ob_dj_survey-0.1.3.dist-info/WHEEL
ob_dj_survey-0.1.3.dist-info/top_level.txt
ob_dj_survey-0.1.3.dist-info/RECORD
